[
    {
        "board_no": 13,
        "article_no": 1297,
        "article_title": "2023년 정보보호교육센터 교육안내",
        "article_text": "<div class=\"fr-view\"><p><img src=\"https://cic.cnu.ac.kr/_res/cic/img/2023정보보호교육안내001.png\" style=\"max-width: 100%; height: auto;\" class=\"fr-fic fr-dii\"></p><p><a href=\"https://sec.keris.or.kr\" target=\"_new\"><img class=\"fr-fic fr-dii\" style=\"height: auto; max-width: 100%;\" src=\"https://cic.cnu.ac.kr/_res/cic/img/2023정보보호교육안내002.png\"></a></p><p><img src=\"https://cic.cnu.ac.kr/_res/cic/img/2023정보보호교육안내_003.png\" style=\"max-width: 100%; height: auto;\" class=\"fr-fic fr-dii\"></p><p><img src=\"https://cic.cnu.ac.kr/_res/cic/img/2023정보보호교육안내_004.png\" style=\"max-width: 100%; height: auto;\" class=\"fr-fic fr-dii\"></p><p><img src=\"https://cic.cnu.ac.kr/_res/cic/img/2023정보보호교육안내005.png\" style=\"max-width: 100%; height: auto;\" class=\"fr-fic fr-dii\"></p></div>",
        "writer_nm": "정보화본부",
        "click_cnt": 98,
        "attach_cnt": 0,
        "update_dt": {
            "date": 4,
            "day": 2,
            "hours": 14,
            "minutes": 50,
            "month": 3,
            "nanos": 0,
            "seconds": 20,
            "time": 1680587420000,
            "timezoneOffset": -540,
            "year": 123
        }
    },
    {
        "board_no": 13,
        "article_no": 7007,
        "article_title": "충남대학교 학내 정보시스템(포탈, 지능형 통합정보시스템, 모바일 등) 개선을 위한 설문조사 참여 요청",
        "article_text": "<div class=\"fr-view\"><p>우리 정보화본부에서는 포탈 시스템, 지능형 통합정보시스템, 모바일 등 학생 및 교수의 불편사항과 기능개선 요구사항을&nbsp;</p><p><br></p><p>검토‧반영하기 위해 아래와 같이 설문을 실시하오니, &nbsp;</p><p><br></p><p>많은 참여 부탁드리겠습니다.&nbsp;</p><p><br></p><p><br></p><p>1. 참여대상 : 학생 및 교수 ※ 직원은 지능형 통합정보시스템 정보화서비스 요청(ITSM)에서 상시적으로 요구사항 접수&nbsp;</p><p><br></p><p>2. 조사기간 : 2023. 3. 31.(금) ~ 4. 14.(금)&nbsp;</p><p><br></p><p>3. 조사내용 : 학생 및 교수 불편사항 및 기능개선 요구사항 수집</p><p><br></p><p>4. 설문조사 URL &nbsp;</p><p><br></p><p><br></p><p><br></p><table style=\"width: 61%; margin-right: calc(39%);\"><tbody><tr><td style=\"width: 10.5725%; height: 17.65pt; padding: 1.41pt 5.1pt; background: rgb(231, 244, 246); vertical-align: middle;\" valign=\"middle\"><p style=\"text-align:center;\"><span style=\"font-family:굴림체;font-weight:bold;font-size:16px;\">구분</span></p></td><td colspan=\"2\" style=\"width: 89.3387%; height: 17.65pt; padding: 1.41pt 5.1pt; background: rgb(231, 244, 246); vertical-align: middle;\" valign=\"middle\"><p style=\"text-align:center;\"><span style=\"font-family:굴림체;font-weight:bold;font-size:16px;\">설문조사&nbsp;</span><span style=\"font-family:굴림체;font-weight:bold;font-size:16px;\">URL</span></p></td></tr><tr><td style=\"width: 10.5725%; height: 28.61pt; padding: 1.41pt 5.1pt; vertical-align: middle; text-align: center;\" valign=\"middle\"><p style=\"margin-right:5.0pt;text-align:center;\"><span style=\"font-family:굴림체;font-weight:bold;\">학생&nbsp;</span></p></td><td style=\"width: 30.1913%; height: 28.61pt; padding: 1.41pt 5.1pt; vertical-align: middle;\" valign=\"middle\"><p style=\"margin-right:5.0pt;font-weight:bold;\"><a href=\"http://tmurl.kr/7i0x\"><u><span style=\"font-family:굴림체;font-weight:bold;color:#0000ff;\">http://tmurl.kr/7i0x</span></u></a></p></td><td style=\"width: 59.0982%; height: 28.61pt; padding: 1.41pt 5.1pt; vertical-align: middle;\" valign=\"middle\"><p style=\"margin-right:5.0pt;text-align:center;font-weight:bold;\"><img src=\"/_attach/image/editor_image/2023/03/ZGTNIhOzUiOpqrVEIQla0.jpg\" class=\"fr-fic fr-dib\" data-path=\"/_attach/image/editor_image/2023/03/ZGTNIhOzUiOpqrVEIQla0.jpg\" data-size=\"7489\" data-success=\"true\" data-file_name=\"ZGTNIhOzUiOpqrVEIQla0.jpg\" data-alt=\"screen shot\"></p></td></tr><tr><td style=\"width: 10.5725%; height: 34.27pt; padding: 1.41pt 5.1pt; vertical-align: middle; text-align: center;\" valign=\"middle\"><p style=\"margin-right:5.0pt;text-align:center;\"><span style=\"font-family:굴림체;font-weight:bold;\">교수</span></p></td><td style=\"width: 30.1913%; height: 34.27pt; padding: 1.41pt 5.1pt; vertical-align: middle;\" valign=\"middle\"><p style=\"margin-right:5.0pt;font-weight:bold;\"><a href=\"http://tmurl.kr/7i0w\"><u><span style=\"font-family:굴림체;font-weight:bold;color:#0000ff;\">http://tmurl.kr/7i0w</span></u></a></p></td><td style=\"width: 59.0982%; height: 34.27pt; padding: 1.41pt 5.1pt; vertical-align: middle;\" valign=\"middle\"><p style=\"margin-right:5.0pt;text-align:center;font-weight:bold;\"><img src=\"/_attach/image/editor_image/2023/03/RDkOTSdmgaIjUqKFxqDJ0.jpg\" class=\"fr-fic fr-dib\" data-path=\"/_attach/image/editor_image/2023/03/RDkOTSdmgaIjUqKFxqDJ0.jpg\" data-size=\"7298\" data-success=\"true\" data-file_name=\"RDkOTSdmgaIjUqKFxqDJ0.jpg\" data-alt=\"screen shot\"></p></td></tr></tbody></table><p><br></p><p><br></p></div>",
        "writer_nm": "정보화본부",
        "click_cnt": 178,
        "attach_cnt": 0,
        "update_dt": {
            "date": 3,
            "day": 1,
            "hours": 9,
            "minutes": 29,
            "month": 3,
            "nanos": 0,
            "seconds": 48,
            "time": 1680481788000,
            "timezoneOffset": -540,
            "year": 123
        }
    }
]
